langchain_alibabacloud_mysql/__init__.py
langchain_alibabacloud_mysql/py.typed
langchain_alibabacloud_mysql/utils/__init__.py
langchain_alibabacloud_mysql/vectorstores/__init__.py
langchain_alibabacloud_mysql/vectorstores/alibabacloud_mysql.py
langchain_alibabacloud_mysql-1.0.1.dist-info/METADATA
langchain_alibabacloud_mysql-1.0.1.dist-info/WHEEL
langchain_alibabacloud_mysql-1.0.1.dist-info/licenses/LICENSE
langchain_alibabacloud_mysql-1.0.1.dist-info/RECORD
