Metadata-Version: 2.4
Name: langchain-alibabacloud-mysql
Version: 1.0.1
Summary: An integration package connecting AlibabaCloud RDS MySQL (with Vector support) and LangChain
License: MIT
License-File: LICENSE
Requires-Python: >=3.10.0,<4.0.0
Classifier: License :: OSI Approved :: MIT License
Classifier: Programming Language :: Python :: 3
Classifier: Programming Language :: Python :: 3.10
Classifier: Programming Language :: Python :: 3.11
Classifier: Programming Language :: Python :: 3.12
Classifier: Programming Language :: Python :: 3.13
Classifier: Programming Language :: Python :: 3.14
Requires-Dist: langchain-core (>=1.0.0)
Requires-Dist: mysql-connector-python (>=8.0.0)
Project-URL: Repository, https://github.com/wangkuahai/langchain-alibabacloud-mysql
Project-URL: Release Notes, https://github.com/wangkuahai/langchain-alibabacloud-mysql/releases
Project-URL: Source Code, https://github.com/wangkuahai/langchain-alibabacloud-mysql/tree/main/libs/alibabacloud_mysql
